hypetext/__init__.py
hypetext/h.py
hypetext/py.typed
hypetext/utils.py
hypetext/version.py
hypetext-0.0.2.dist-info/METADATA
hypetext-0.0.2.dist-info/WHEEL
hypetext-0.0.2.dist-info/RECORD
