Metadata-Version: 2.4
Name: hypetext
Version: 0.0.2
Summary: HTML generation based on template strings
Project-URL: Homepage, https://github.com/breuleux/hypetext
Project-URL: Repository, https://github.com/breuleux/hypetext
Author-email: Olivier Breuleux <breuleux@gmail.com>
Requires-Python: >=3.14
Requires-Dist: ovld>=0.5.10
